pig_gguf/__init__.py
pig_gguf/b.py
pig_gguf/d.py
pig_gguf/e.py
pig_gguf/f.py
pig_gguf-0.0.5.dist-info/LICENSE
pig_gguf-0.0.5.dist-info/WHEEL
pig_gguf-0.0.5.dist-info/METADATA
pig_gguf-0.0.5.dist-info/RECORD
