Metadata-Version: 2.1
Name: pig-gguf
Version: 0.0.5
Summary: pig tool for gguf
Author-email: gguf <info@gguf.us>
Classifier: License :: OSI Approved :: MIT License
Requires-Dist: gguf-connector
Project-URL: Repository, https://github.com/gguf-org/pig
